{
  "Austria": {
    "name": "Austria",
    "population": "8842000",
    "eurozoneStatus": "true"
  },
  "Belgium": {
    "name": "Belgium",
    "population": "11467923",
    "eurozoneStatus": "true"
  },
  "Bulgaria": {
    "name": "Bulgaria",
    "population": "7000039",
    "eurozoneStatus": "false"
  },
  "Croatia": {
    "name": "Croatia",
    "population": "4076246",
    "eurozoneStatus": "false"
  },
  "Cyprus": {
    "name": "Cyprus",
    "population": "875898",
    "eurozoneStatus": "true"
  },
  "Czech": {
    "name": "Czech Republic",
    "population": "10528984",
    "eurozoneStatus": "false"
  },
  "Denmark": {
    "name": "Denmark",
    "population": "5799763",
    "eurozoneStatus": "false"
  },
  "Estonia": {
    "name": "Estonia",
    "population": "1324820",
    "eurozoneStatus": "true"
  },
  "Finland": {
    "name": "Finland",
    "population": "5512119",
    "eurozoneStatus": "true"
  },
  "France": {
    "name": "France",
    "population": "67028048",
    "eurozoneStatus": "true"
  },
  "Germany": {
    "name": "Germany",
    "population": "82940663",
    "eurozoneStatus": "true"
  },
  "Greece": {
    "name": "Greece",
    "population": "10722287",
    "eurozoneStatus": "true"
  },
  "Hungary": {
    "name": "Hungary",
    "population": "9772756",
    "eurozoneStatus": "false"
  },
  "Ireland": {
    "name": "Ireland",
    "population": "4904240",
    "eurozoneStatus": "true"
  },
  "Italy": {
    "name": "Italy",
    "population": "61068437",
    "eurozoneStatus": "true"
  },
  "Latvia": {
    "name": "Latvia",
    "population": "1919968",
    "eurozoneStatus": "true"
  },
  "Lithuania": {
    "name": "Lithuania",
    "population": "2794184",
    "eurozoneStatus": "true"
  },
  "Luxembourg": {
    "name": "Luxembourg",
    "population": "612179",
    "eurozoneStatus": "true"
  },
  "Malta": {
    "name": "Malta",
    "population": "493559",
    "eurozoneStatus": "true"
  },
  "Netherlands": {
    "name": "Netherlands",
    "population": "17423013",
    "eurozoneStatus": "true"
  },
  "Poland": {
    "name": "Poland",
    "population": "37972812",
    "eurozoneStatus": "false"
  },
  "Portugal": {
    "name": "Portugal",
    "population": "10276617",
    "eurozoneStatus": "true"
  },
  "Romania": {
    "name": "Romania",
    "population": "19405156",
    "eurozoneStatus": "false"
  },
  "Slovakia": {
    "name": "Slovakia",
    "population": "5450421",
    "eurozoneStatus": "true"
  },
  "Slovenia": {
    "name": "Slovenia",
    "population": "2080908",
    "eurozoneStatus": "true"
  },
  "Spain": {
    "name": "Spain",
    "population": "46934632",
    "eurozoneStatus": "true"
  },
  "Sweden": {
    "name": "Sweden",
    "population": "10243000",
    "eurozoneStatus": "false"
  }
} 
